da_rover/__init__.py
da_rover/rover.py
da_rover/runner.py
da_rover/version.py
da_rover-1.7.dist-info/LICENSE
da_rover-1.7.dist-info/METADATA
da_rover-1.7.dist-info/WHEEL
da_rover-1.7.dist-info/entry_points.txt
da_rover-1.7.dist-info/top_level.txt
da_rover-1.7.dist-info/RECORD
