Metadata-Version: 2.1
Name: da-rover
Version: 1.7
Summary: Custom Integration Bridge between tools like CA ARD, HP QC/ALM and ALM Octane
Home-page: https://github.com/raka2407/octane-transformer.git
Author: Rakesh Ummadisetty
Author-email: u.rakesh@live.com
License: MIT
Keywords: ard alm qc octane
Platform: any
Classifier: Development Status :: 5 - Production/Stable
Classifier: License :: OSI Approved :: Apache Software License
Classifier: Operating System :: OS Independent
Classifier: Programming Language :: Python :: 3
Classifier: Topic :: Software Development :: Testing
Classifier: Framework :: Robot Framework :: Library
Requires-Dist: pandas (==0.25.0)
Requires-Dist: pyfiglet
Requires-Dist: xlrd
